LICENSE
MANIFEST.in
README.md
requirements.txt
setup.py
autoum/__init__.py
autoum.egg-info/PKG-INFO
autoum.egg-info/SOURCES.txt
autoum.egg-info/dependency_links.txt
autoum.egg-info/requires.txt
autoum.egg-info/top_level.txt
autoum.egg-info/zip-safe
autoum/approaches/__init__.py
autoum/approaches/bayesian_causal_forest.py
autoum/approaches/class_variable_transformation.py
autoum/approaches/generalized_random_forest.py
autoum/approaches/lais_generalization.py
autoum/approaches/r_learner.py
autoum/approaches/s_learner.py
autoum/approaches/traditional.py
autoum/approaches/treatment_dummy.py
autoum/approaches/two_model.py
autoum/approaches/uplift_random_forest.py
autoum/approaches/utils.py
autoum/approaches/x_learner.py
autoum/const/__init__.py
autoum/const/const.py
autoum/datasets/__init__.py
autoum/datasets/criteo.py
autoum/datasets/hillstrom.py
autoum/datasets/lenta.py
autoum/datasets/socialpressure.py
autoum/datasets/starbucks.py
autoum/datasets/utils.py
autoum/datasets/data/__init__.py
autoum/datasets/data/data.zip
autoum/datasets/data/hillstrom.csv.zip
autoum/datasets/data/starbucks.zip
autoum/evaluation/__init__.py
autoum/evaluation/evaluation.py
autoum/evaluation/statistics.py
autoum/pipelines/__init__.py
autoum/pipelines/pipeline_rw.py
autoum/pipelines/pipeline_sd.py
autoum/pipelines/utils.py
docs/requirements.txt
docs/_build/html/_sources/about.rst.txt
docs/_build/html/_sources/autoum.approaches.rst.txt
docs/_build/html/_sources/autoum.const.rst.txt
docs/_build/html/_sources/autoum.datasets.data.rst.txt
docs/_build/html/_sources/autoum.datasets.rst.txt
docs/_build/html/_sources/autoum.evaluation.rst.txt
docs/_build/html/_sources/autoum.pipelines.rst.txt
docs/_build/html/_sources/autoum.rst.txt
docs/_build/html/_sources/examples.rst.txt
docs/_build/html/_sources/index.rst.txt
docs/_build/html/_sources/installation.rst.txt
docs/_build/html/_sources/modules.rst.txt
docs/_build/html/_sources/setup.rst.txt
docs/_build/html/_sources/tests.rst.txt