Metadata-Version: 2.1
Name: autoum
Version: 1.0.1
Summary: A Python Framework for Automatically Evaluating various Uplift Modeling Algorithms to Estimate Individual Treatment Effects
Home-page: https://github.com/jroessler/autoum
Author: Jannik Rößler
Author-email: 
License: UNKNOWN
Platform: UNKNOWN
Classifier: Programming Language :: Python
Classifier: License :: OSI Approved :: Apache Software License
Classifier: Operating System :: OS Independent
Requires-Python: >=3.8
License-File: LICENSE
